odoo8_addon_l10n_ar_chart_of_account-8.0.1.0.0-py2.7-nspkg.pth
odoo_addons/l10n_ar_chart_of_account/account_chart.xml
odoo_addons/l10n_ar_chart_of_account/__openerp__.py
odoo_addons/l10n_ar_chart_of_account/fiscal_templates.xml
odoo_addons/l10n_ar_chart_of_account/account_tax.xml
odoo_addons/l10n_ar_chart_of_account/__init__.py
odoo_addons/l10n_ar_chart_of_account/account_tax_code.xml
odoo_addons/l10n_ar_chart_of_account/l10n_chart_ar_wizard.xml
odoo8_addon_l10n_ar_chart_of_account-8.0.1.0.0.dist-info/top_level.txt
odoo8_addon_l10n_ar_chart_of_account-8.0.1.0.0.dist-info/WHEEL
odoo8_addon_l10n_ar_chart_of_account-8.0.1.0.0.dist-info/RECORD
odoo8_addon_l10n_ar_chart_of_account-8.0.1.0.0.dist-info/metadata.json
odoo8_addon_l10n_ar_chart_of_account-8.0.1.0.0.dist-info/DESCRIPTION.rst
odoo8_addon_l10n_ar_chart_of_account-8.0.1.0.0.dist-info/METADATA
odoo8_addon_l10n_ar_chart_of_account-8.0.1.0.0.dist-info/namespace_packages.txt
